gradio_image_annotation_v2/__init__.py
gradio_image_annotation_v2/image_annotator.py
gradio_image_annotation_v2/image_annotator.pyi
gradio_image_annotation_v2/templates/component/index.js
gradio_image_annotation_v2/templates/component/style.css
gradio_image_annotation_v2/templates/example/index.js
gradio_image_annotation_v2/templates/example/style.css
gradio_image_annotation_v2-0.2.2.dist-info/METADATA
gradio_image_annotation_v2-0.2.2.dist-info/WHEEL
gradio_image_annotation_v2-0.2.2.dist-info/licenses/LICENSE
gradio_image_annotation_v2-0.2.2.dist-info/RECORD
