Metadata-Version: 2.4
Name: gradio_image_annotation_v2
Version: 0.2.2
Summary: A Gradio component that can be used to annotate images with bounding boxes and point.
Project-URL: Homepage, https://github.com/yama-is-bocchi/gradio_image_annotator_v2
Project-URL: Repository, https://github.com/yama-is-bocchi/gradio_image_annotator_v2
Author: yama-is-bocchi
License-Expression: MIT
License-File: LICENSE
Keywords: annotate,annotator,bounding box,boxes,gradio-custom-component,gradio-template-Image
Classifier: Development Status :: 3 - Alpha
Classifier: License :: OSI Approved :: Apache Software License
Classifier: Operating System :: OS Independent
Classifier: Programming Language :: Python :: 3
Classifier: Programming Language :: Python :: 3 :: Only
Classifier: Programming Language :: Python :: 3.8
Classifier: Programming Language :: Python :: 3.9
Classifier: Programming Language :: Python :: 3.10
Classifier: Programming Language :: Python :: 3.11
Classifier: Topic :: Scientific/Engineering
Classifier: Topic :: Scientific/Engineering :: Artificial Intelligence
Classifier: Topic :: Scientific/Engineering :: Visualization
Requires-Python: >=3.8
Requires-Dist: gradio<6.0,>=4.29
Provides-Extra: dev
Requires-Dist: build; extra == 'dev'
Requires-Dist: twine; extra == 'dev'
